python_gtmetrix2/__init__.py
python_gtmetrix2/_internals.py
python_gtmetrix2/exceptions.py
python_gtmetrix2-0.3.1.dist-info/LICENSE
python_gtmetrix2-0.3.1.dist-info/METADATA
python_gtmetrix2-0.3.1.dist-info/WHEEL
python_gtmetrix2-0.3.1.dist-info/top_level.txt
python_gtmetrix2-0.3.1.dist-info/RECORD
