Metadata-Version: 2.1
Name: python-gtmetrix2
Version: 0.3.1
Summary: A Python client library for GTmetrix REST API v2.0
Home-page: https://github.com/Lex-2008/python-gtmetrix2
Author: Alexey Shpakovsky
Author-email: alexey+setup.py@shpakovsky.ru
License: UNKNOWN
Project-URL: Documentation, https://python-gtmetrix2.readthedocs.io/
Keywords: python gtmetrix performance lighthouse pagespeed yslow
Platform: UNKNOWN
Classifier: Development Status :: 4 - Beta
Classifier: Environment :: Web Environment
Classifier: Intended Audience :: Developers
Classifier: License :: OSI Approved :: MIT License
Classifier: Operating System :: OS Independent
Classifier: Programming Language :: Python
Classifier: Programming Language :: Python :: 3
Classifier: Programming Language :: Python :: 3.5
Classifier: Programming Language :: Python :: 3.6
Classifier: Programming Language :: Python :: 3.7
Classifier: Programming Language :: Python :: 3.8
Classifier: Programming Language :: Python :: 3.9
Classifier: Topic :: Internet :: WWW/HTTP :: Site Management
Classifier: Topic :: Software Development :: Libraries :: Python Modules
Requires-Python: >=3.5
License-File: LICENSE
